unitair/__init__.py
unitair/initializations.py
unitair/utils.py
unitair/gates/__init__.py
unitair/gates/gate_construction.py
unitair/gates/gates.py
unitair/gates/matrix_algebra.py
unitair/simulation/__init__.py
unitair/simulation/measurement.py
unitair/simulation/operations.py
unitair/simulation/utils.py
unitair/states/__init__.py
unitair/states/conversions.py
unitair/states/innerprod.py
unitair/states/shapes.py
unitair-0.3.0.dist-info/LICENSE
unitair-0.3.0.dist-info/METADATA
unitair-0.3.0.dist-info/WHEEL
unitair-0.3.0.dist-info/top_level.txt
unitair-0.3.0.dist-info/RECORD
