Metadata-Version: 2.1
Name: unitair
Version: 0.3.0
Summary: PyTorch-based quantum computing
Home-page: https://github.com/qcware/qcware-unitair.git
Author: QC Ware Corp. (Sean Weinberg, Fabio Sanches)
Author-email: sean.weinberg@qcware.com
License: APACHE LICENSE, VERSION 2.0
Platform: UNKNOWN
Classifier: Programming Language :: Python :: 3
Classifier: License :: OSI Approved :: Apache Software License
Requires-Python: >=3.7
License-File: LICENSE
Requires-Dist: torch (>=1.8.1)
Requires-Dist: decorator (>=4.4.2)
Requires-Dist: numpy (>=1.21.0)
Requires-Dist: setuptools (>=53.0.0)
Provides-Extra: test
Requires-Dist: hypothesis (>=6.14.0) ; extra == 'test'
Requires-Dist: pytest ; extra == 'test'
